Metadata-Version: 2.1
Name: savager
Version: 0.1
Summary: create SVG files with python scripts
Home-page: https://gitlab.com/pyrogue6/savager.git
Maintainer: Sabrina Held
Maintainer-email: pyrogue6@gmail.com
License: MIT License
Download-URL: https://gitlab.com/pyrogue6/savager/-/archive/0.1/savager-0.1.tar.gz
Keywords: svg
Platform: UNKNOWN
Classifier: Development Status :: 1 - Planning
Classifier: License :: OSI Approved :: MIT License
Classifier: Programming Language :: Python :: 3.7
Classifier: Programming Language :: Python :: 3.8
Classifier: Topic :: Multimedia :: Graphics
Classifier: Topic :: Artistic Software
Requires-Python: >=3
